LICENSE.rst
MANIFEST.in
README.rst
setup.py
bin/xunitmerge
xunitmerge/__init__.py
xunitmerge/xmerge.py
xunitmerge.egg-info/PKG-INFO
xunitmerge.egg-info/SOURCES.txt
xunitmerge.egg-info/dependency_links.txt
xunitmerge.egg-info/requires.txt
xunitmerge.egg-info/top_level.txt