Metadata-Version: 1.1
Name: xunitmerge
Version: 1.0.4
Summary: Utility for merging multiple XUnit xml reports into a single xml report.
Home-page: https://github.com/miki725/xunitmerge
Author: Miroslav Shubernetskiy
Author-email: miroslav@miki725.com
License: MIT
Keywords: x,u,n,i,t, ,r,e,p,o,r,t,s
Platform: UNKNOWN
Classifier: Programming Language :: Python
Classifier: Programming Language :: Python :: 3
Classifier: Development Status :: 4 - Beta
Classifier: Intended Audience :: Developers
Classifier: Topic :: Software Development :: Libraries :: Python Modules
Classifier: Topic :: Software Development :: Testing
